ngff_zarr_mcp/__about__.py
ngff_zarr_mcp/__init__.py
ngff_zarr_mcp/models.py
ngff_zarr_mcp/server.py
ngff_zarr_mcp/tools.py
ngff_zarr_mcp/utils.py
ngff_zarr_mcp-0.5.0.dist-info/METADATA
ngff_zarr_mcp-0.5.0.dist-info/WHEEL
ngff_zarr_mcp-0.5.0.dist-info/entry_points.txt
ngff_zarr_mcp-0.5.0.dist-info/RECORD
