Metadata-Version: 2.4
Name: ngff-zarr-mcp
Version: 0.5.0
Summary: Model Context Protocol server for OME-Zarr image conversion
Project-URL: Documentation, https://github.com/thewtex/ngff-zarr#readme
Project-URL: Issues, https://github.com/thewtex/ngff-zarr/issues
Project-URL: Source, https://github.com/thewtex/ngff-zarr
Author-email: Matt McCormick <matt@fideus.io>
License-Expression: MIT
Keywords: image-conversion,mcp,microscopy,ome-zarr
Classifier: Development Status :: 4 - Beta
Classifier: Intended Audience :: Developers
Classifier: Intended Audience :: Science/Research
Classifier: License :: OSI Approved :: MIT License
Classifier: Operating System :: OS Independent
Classifier: Programming Language :: Python
Classifier: Programming Language :: Python :: 3
Classifier: Programming Language :: Python :: 3 :: Only
Classifier: Programming Language :: Python :: 3.9
Classifier: Programming Language :: Python :: 3.10
Classifier: Programming Language :: Python :: 3.11
Classifier: Programming Language :: Python :: 3.12
Classifier: Programming Language :: Python :: 3.13
Classifier: Programming Language :: Python :: Implementation :: CPython
Classifier: Topic :: Scientific/Engineering
Requires-Python: >=3.9
Requires-Dist: aiofiles
Requires-Dist: aiohttp
Requires-Dist: httpx
Requires-Dist: mcp
Requires-Dist: ngff-zarr[cli,tensorstore]>=0.15.2
Requires-Dist: pathvalidate
Requires-Dist: pydantic>=2.0
Requires-Dist: requests
Provides-Extra: all
Requires-Dist: gcsfs; extra == 'all'
Requires-Dist: ngff-zarr[all]; extra == 'all'
Requires-Dist: s3fs; extra == 'all'
Provides-Extra: cloud
Requires-Dist: gcsfs; extra == 'cloud'
Requires-Dist: s3fs; extra == 'cloud'
Provides-Extra: dev
Requires-Dist: black>=23.1.0; extra == 'dev'
Requires-Dist: hatch; extra == 'dev'
Requires-Dist: mypy>=1.0.0; extra == 'dev'
Requires-Dist: pytest; extra == 'dev'
Requires-Dist: pytest-asyncio; extra == 'dev'
Requires-Dist: pytest-cov; extra == 'dev'
Requires-Dist: ruff>=0.0.243; extra == 'dev'
Requires-Dist: types-aiofiles; extra == 'dev'
Requires-Dist: types-psutil; extra == 'dev'
